websc_client/__init__.py
websc_client/client.py
websc_client/exceptions.py
websc_client/websc.py
websc_client-1.0.4.dist-info/METADATA
websc_client-1.0.4.dist-info/WHEEL
websc_client-1.0.4.dist-info/top_level.txt
websc_client-1.0.4.dist-info/RECORD
