Metadata-Version: 2.1
Name: websc-client
Version: 1.0.4
Summary: Library for communicate with websc
Author-email: Patrik Kratochvil <info@ledsc.eu>
Project-URL: homepage, https://ledsc.eu/websc/
Project-URL: repository, https://gitlab.com/ledsc/websclient
Classifier: Programming Language :: Python :: 3
Classifier: License :: OSI Approved :: MIT License
Classifier: Operating System :: OS Independent
Requires-Python: >=3.8
Requires-Dist: websockets ~=12.0
